thinking_modules/__init__.py
thinking_modules/definitions.py
thinking_modules/immutable.py
thinking_modules/main_module.py
thinking_modules/model.py
thinking_modules/scan.py
thinking_modules-0.0.4.dist-info/LICENSE
thinking_modules-0.0.4.dist-info/METADATA
thinking_modules-0.0.4.dist-info/WHEEL
thinking_modules-0.0.4.dist-info/top_level.txt
thinking_modules-0.0.4.dist-info/RECORD
