Metadata-Version: 2.1
Name: thinking-modules
Version: 0.0.4
Summary: Module-related python utilities - recursive package scan, modeling of names and modules, etc
Author-email: Filip Malczak <filip.malczak@gmail.com>
License: MIT License
Project-URL: Homepage, https://github.com/FilipMalczak/thinking-modules
Keywords: thinking,import,scan,modules,meta
Classifier: License :: OSI Approved :: MIT License
Classifier: Programming Language :: Python
Classifier: Programming Language :: Python :: 3
Classifier: Topic :: Software Development :: Libraries
Classifier: Typing :: Typed
Requires-Python: >=3.12
License-File: LICENSE
Requires-Dist: lazy==1.6
